license_lib/__init__.py
license_lib/binding_id.py
license_lib/features.py
license_lib/get_binding_id.py
license_lib/utils.py
license_lib/validator.py
license_lib/version.py
license_lib_client-0.1.0.dist-info/licenses/LICENSE
license_lib_client-0.1.0.dist-info/METADATA
license_lib_client-0.1.0.dist-info/WHEEL
license_lib_client-0.1.0.dist-info/entry_points.txt
license_lib_client-0.1.0.dist-info/top_level.txt
license_lib_client-0.1.0.dist-info/RECORD
