Metadata-Version: 2.4
Name: license-lib-client
Version: 0.1.0
Summary: A comprehensive license validation library with hardware binding
Author-email: Fexo <hello@fexo.io>
License: MIT
Project-URL: Homepage, https://github.com/Fexo-1/license-client
Project-URL: Repository, https://github.com/Fexo-1/license-client.git
Project-URL: Issues, https://github.com/Fexo-1/license-client/issues
Project-URL: Documentation, https://github.com/Fexo-1/license-client/blob/main/docs/USER_MANUAL.md
Project-URL: Changelog, https://github.com/Fexo-1/license-client/blob/main/CHANGELOG.md
Keywords: license,validation,hardware-binding,cryptography
Classifier: Development Status :: 4 - Beta
Classifier: Intended Audience :: Developers
Classifier: License :: OSI Approved :: MIT License
Classifier: Programming Language :: Python :: 3
Classifier: Programming Language :: Python :: 3.8
Classifier: Programming Language :: Python :: 3.9
Classifier: Programming Language :: Python :: 3.10
Classifier: Programming Language :: Python :: 3.11
Classifier: Programming Language :: Python :: 3.12
Classifier: Programming Language :: Python :: 3.13
Classifier: Topic :: Software Development :: Libraries :: Python Modules
Classifier: Topic :: Security
Requires-Python: >=3.8
License-File: LICENSE
Requires-Dist: cryptography>=3.4.8
Requires-Dist: watchdog>=2.1.9
Provides-Extra: dev
Requires-Dist: pytest>=7.0.0; extra == "dev"
Requires-Dist: pytest-cov>=4.0.0; extra == "dev"
Requires-Dist: pytest-mock>=3.10.0; extra == "dev"
Requires-Dist: tox>=4.0.0; extra == "dev"
Dynamic: license-file
